<?xml version="1.0" encoding="UTF-8"?>
<!DOCTYPE plist PUBLIC "-//Apple//DTD PLIST 1.0//EN" "http://www.apple.com/DTDs/PropertyList-1.0.dtd"/>

<plist version="1.0">
    <dict>
        <key>ROOT</key>
        <array>
            <dict>
                <key>id</key>
                <string>1382</string>
            </dict>
            <dict>
                <key>id</key>
                <string>1838</string>
                <key>Image</key>
                <dict>
                    <key>value</key>
                    <string>1836</string>
                </dict>
            </dict>
            <dict>
                <key>id</key>
                <string>1844</string>
                <key>Image</key>
                <dict>
                    <key>value</key>
                    <string>1845</string>
                </dict>
            </dict>
            <dict>
                <key>id</key>
                <string>1853</string>
                <key>Image</key>
                <dict>
                    <key>value</key>
                    <string>2246</string>
                </dict>
            </dict>
            <dict>
                <key>id</key>
                <string>1857</string>
                <key>Image</key>
                <dict>
                    <key>value</key>
                    <string>1858</string>
                </dict>
            </dict>
            <dict>
                <key>id</key>
                <string>1862</string>
                <key>Image</key>
                <dict>
                    <key>value</key>
                    <string>2275</string>
                </dict>
            </dict>
            <dict>
                <key>id</key>
                <string>1866</string>
                <key>Image</key>
                <dict>
                    <key>value</key>
                    <string>1858</string>
                </dict>
            </dict>
            <dict>
                <key>id</key>
                <string>1869</string>
                <key>Image</key>
                <dict>
                    <key>value</key>
                    <string>2269</string>
                </dict>
            </dict>
            <dict>
                <key>id</key>
                <string>1884</string>
                <key>Image</key>
                <dict>
                    <key>value</key>
                    <string>1882</string>
                </dict>
            </dict>
            <dict>
                <key>id</key>
                <string>1887</string>
                <key>Image</key>
                <dict>
                    <key>value</key>
                    <string>1885</string>
                </dict>
            </dict>
            <dict>
                <key>id</key>
                <string>1890</string>
                <key>Image</key>
                <dict>
                    <key>value</key>
                    <string>1888</string>
                </dict>
            </dict>
            <dict>
                <key>id</key>
                <string>1900</string>
                <key>Image</key>
                <dict>
                    <key>value</key>
                    <string>1898</string>
                </dict>
            </dict>
            <dict>
                <key>id</key>
                <string>1901</string>
                <key>Image</key>
                <dict>
                    <key>value</key>
                    <string>3535</string>
                </dict>
            </dict>
            <dict>
                <key>id</key>
                <string>1902</string>
                <key>Image</key>
                <dict>
                    <key>value</key>
                    <string>1888</string>
                </dict>
            </dict>
            <dict>
                <key>id</key>
                <string>1931</string>
                <key>Image</key>
                <dict>
                    <key>value</key>
                    <string>1845</string>
                </dict>
            </dict>
            <dict>
                <key>id</key>
                <string>1958</string>
                <key>Image</key>
                <dict>
                    <key>value</key>
                    <string>1845</string>
                </dict>
            </dict>
            <dict>
                <key>id</key>
                <string>1985</string>
                <key>Image</key>
                <dict>
                    <key>value</key>
                    <string>1845</string>
                </dict>
            </dict>
            <dict>
                <key>id</key>
                <string>1988</string>
                <key>Image</key>
                <dict>
                    <key>value</key>
                    <string>2304</string>
                </dict>
            </dict>
            <dict>
                <key>id</key>
                <string>1991</string>
                <key>Image</key>
                <dict>
                    <key>value</key>
                    <string>2310</string>
                </dict>
            </dict>
            <dict>
                <key>id</key>
                <string>1998</string>
                <key>Image</key>
                <dict>
                    <key>value</key>
                    <string>2316</string>
                </dict>
            </dict>
        </array>
    </dict>
</plist>
