<?xml version="1.0" encoding="UTF-8"?>
<!DOCTYPE plist PUBLIC "-//Apple//DTD PLIST 1.0//EN" "http://www.apple.com/DTDs/PropertyList-1.0.dtd"/>

<plist version="1.0">
    <dict>
        <key>ROOT</key>
        <array>
            <dict>
                <key>id</key>
                <string>105</string>
                <key>sprites</key>
                <array>
                    <string>106</string>
                </array>
            </dict>
            <dict>
                <key>id</key>
                <string>120</string>
                <key>sprites</key>
                <array>
                    <string>121</string>
                </array>
            </dict>
            <dict>
                <key>id</key>
                <string>341</string>
                <key>sprites</key>
                <array>
                    <string>342</string>
                </array>
            </dict>
            <dict>
                <key>id</key>
                <string>441</string>
                <key>sprites</key>
                <array>
                    <string>442</string>
                </array>
            </dict>
            <dict>
                <key>id</key>
                <string>1042</string>
                <key>sprites</key>
                <array>
                    <string>1043</string>
                </array>
            </dict>
            <dict>
                <key>id</key>
                <string>1050</string>
                <key>sprites</key>
                <array>
                    <string>1051</string>
                </array>
            </dict>
            <dict>
                <key>id</key>
                <string>1186</string>
                <key>sprites</key>
                <array>
                    <string>1187</string>
                </array>
            </dict>
            <dict>
                <key>id</key>
                <string>1448</string>
                <key>sprites</key>
                <array>
                    <string>1449</string>
                </array>
            </dict>
            <dict>
                <key>id</key>
                <string>1592</string>
                <key>sprites</key>
                <array>
                    <string>1593</string>
                </array>
            </dict>
            <dict>
                <key>id</key>
                <string>1601</string>
                <key>sprites</key>
                <array>
                    <string>1602</string>
                </array>
            </dict>
            <dict>
                <key>id</key>
                <string>1693</string>
                <key>sprites</key>
                <array>
                    <string>1694</string>
                </array>
            </dict>
            <dict>
                <key>id</key>
                <string>1713</string>
                <key>sprites</key>
                <array>
                    <string>1714</string>
                </array>
            </dict>
            <dict>
                <key>id</key>
                <string>1771</string>
                <key>sprites</key>
                <array>
                    <string>1772</string>
                </array>
            </dict>
            <dict>
                <key>id</key>
                <string>1777</string>
                <key>sprites</key>
                <array>
                    <string>1778</string>
                </array>
            </dict>
            <dict>
                <key>id</key>
                <string>1836</string>
                <key>sprites</key>
                <array>
                    <string>1837</string>
                </array>
            </dict>
            <dict>
                <key>id</key>
                <string>1842</string>
                <key>sprites</key>
                <array>
                    <string>1843</string>
                </array>
            </dict>
            <dict>
                <key>id</key>
                <string>1845</string>
                <key>sprites</key>
                <array>
                    <string>1846</string>
                </array>
            </dict>
            <dict>
                <key>id</key>
                <string>1850</string>
                <key>sprites</key>
                <array>
                    <string>1851</string>
                </array>
            </dict>
            <dict>
                <key>id</key>
                <string>1858</string>
                <key>sprites</key>
                <array>
                    <string>1859</string>
                </array>
            </dict>
            <dict>
                <key>id</key>
                <string>1860</string>
                <key>sprites</key>
                <array>
                    <string>1861</string>
                </array>
            </dict>
            <dict>
                <key>id</key>
                <string>1867</string>
                <key>sprites</key>
                <array>
                    <string>1868</string>
                </array>
            </dict>
            <dict>
                <key>id</key>
                <string>1873</string>
                <key>sprites</key>
                <array>
                    <string>1874</string>
                </array>
            </dict>
            <dict>
                <key>id</key>
                <string>1879</string>
                <key>sprites</key>
                <array>
                    <string>1880</string>
                </array>
            </dict>
            <dict>
                <key>id</key>
                <string>1882</string>
                <key>sprites</key>
                <array>
                    <string>1883</string>
                </array>
            </dict>
            <dict>
                <key>id</key>
                <string>1885</string>
                <key>sprites</key>
                <array>
                    <string>1886</string>
                </array>
            </dict>
            <dict>
                <key>id</key>
                <string>1888</string>
                <key>sprites</key>
                <array>
                    <string>1889</string>
                </array>
            </dict>
            <dict>
                <key>id</key>
                <string>1895</string>
                <key>sprites</key>
                <array>
                    <string>1896</string>
                </array>
            </dict>
            <dict>
                <key>id</key>
                <string>1898</string>
                <key>sprites</key>
                <array>
                    <string>1899</string>
                </array>
            </dict>
            <dict>
                <key>id</key>
                <string>1986</string>
                <key>sprites</key>
                <array>
                    <string>1987</string>
                </array>
            </dict>
            <dict>
                <key>id</key>
                <string>1989</string>
                <key>sprites</key>
                <array>
                    <string>1990</string>
                </array>
            </dict>
            <dict>
                <key>id</key>
                <string>2020</string>
                <key>sprites</key>
                <array>
                    <string>2021</string>
                </array>
            </dict>
            <dict>
                <key>id</key>
                <string>2108</string>
                <key>sprites</key>
                <array>
                    <string>2109</string>
                    <string>2110</string>
                    <string>2111</string>
                    <string>2112</string>
                    <string>2113</string>
                    <string>2114</string>
                    <string>2115</string>
                    <string>2116</string>
                    <string>2118</string>
                </array>
            </dict>
            <dict>
                <key>id</key>
                <string>2133</string>
                <key>sprites</key>
                <array>
                    <string>2134</string>
                    <string>2135</string>
                    <string>2136</string>
                    <string>2137</string>
                    <string>2138</string>
                    <string>2139</string>
                    <string>2140</string>
                    <string>2141</string>
                    <string>2142</string>
                    <string>2143</string>
                </array>
            </dict>
            <dict>
                <key>id</key>
                <string>2159</string>
                <key>sprites</key>
                <array>
                    <string>2160</string>
                    <string>2161</string>
                    <string>2162</string>
                    <string>2163</string>
                    <string>2164</string>
                    <string>2165</string>
                    <string>2166</string>
                    <string>2167</string>
                    <string>2168</string>
                    <string>2169</string>
                </array>
            </dict>
            <dict>
                <key>id</key>
                <string>2185</string>
                <key>sprites</key>
                <array>
                    <string>2186</string>
                    <string>2187</string>
                    <string>2189</string>
                    <string>2190</string>
                    <string>2191</string>
                    <string>2192</string>
                    <string>2193</string>
                    <string>2194</string>
                </array>
            </dict>
            <dict>
                <key>id</key>
                <string>2208</string>
                <key>sprites</key>
                <array>
                    <string>2209</string>
                    <string>2210</string>
                    <string>2211</string>
                </array>
            </dict>
            <dict>
                <key>id</key>
                <string>2223</string>
                <key>sprites</key>
                <array>
                    <string>2224</string>
                    <string>2225</string>
                    <string>2226</string>
                    <string>2227</string>
                    <string>2228</string>
                </array>
            </dict>
            <dict>
                <key>id</key>
                <string>2246</string>
                <key>sprites</key>
                <array>
                    <string>2247</string>
                    <string>2248</string>
                    <string>2249</string>
                    <string>2250</string>
                </array>
            </dict>
            <dict>
                <key>id</key>
                <string>2258</string>
                <key>sprites</key>
                <array>
                    <string>2259</string>
                </array>
            </dict>
            <dict>
                <key>id</key>
                <string>2263</string>
                <key>sprites</key>
                <array>
                    <string>2264</string>
                </array>
            </dict>
            <dict>
                <key>id</key>
                <string>2269</string>
                <key>sprites</key>
                <array>
                    <string>2270</string>
                </array>
            </dict>
            <dict>
                <key>id</key>
                <string>2275</string>
                <key>sprites</key>
                <array>
                    <string>2276</string>
                </array>
            </dict>
            <dict>
                <key>id</key>
                <string>2287</string>
                <key>sprites</key>
                <array>
                    <string>2288</string>
                </array>
            </dict>
            <dict>
                <key>id</key>
                <string>2299</string>
                <key>sprites</key>
                <array>
                    <string>2300</string>
                </array>
            </dict>
            <dict>
                <key>id</key>
                <string>2304</string>
                <key>sprites</key>
                <array>
                    <string>2305</string>
                </array>
            </dict>
            <dict>
                <key>id</key>
                <string>2310</string>
                <key>sprites</key>
                <array>
                    <string>2311</string>
                </array>
            </dict>
            <dict>
                <key>id</key>
                <string>2316</string>
                <key>sprites</key>
                <array>
                    <string>2317</string>
                </array>
            </dict>
            <dict>
                <key>id</key>
                <string>2324</string>
                <key>sprites</key>
                <array>
                    <string>2325</string>
                    <string>2326</string>
                    <string>2327</string>
                    <string>2328</string>
                    <string>2329</string>
                    <string>2330</string>
                </array>
            </dict>
            <dict>
                <key>id</key>
                <string>2372</string>
                <key>sprites</key>
                <array>
                    <string>2373</string>
                </array>
            </dict>
            <dict>
                <key>id</key>
                <string>2436</string>
                <key>sprites</key>
                <array>
                    <string>2437</string>
                </array>
            </dict>
            <dict>
                <key>id</key>
                <string>2449</string>
                <key>sprites</key>
                <array>
                    <string>2450</string>
                </array>
            </dict>
            <dict>
                <key>id</key>
                <string>2492</string>
                <key>sprites</key>
                <array>
                    <string>2493</string>
                </array>
            </dict>
            <dict>
                <key>id</key>
                <string>2596</string>
                <key>sprites</key>
                <array>
                    <string>2597</string>
                </array>
            </dict>
            <dict>
                <key>id</key>
                <string>2762</string>
                <key>sprites</key>
                <array>
                    <string>2763</string>
                </array>
            </dict>
            <dict>
                <key>id</key>
                <string>2824</string>
                <key>sprites</key>
                <array>
                    <string>2825</string>
                    <string>2826</string>
                    <string>2827</string>
                    <string>2829</string>
                    <string>2830</string>
                    <string>2831</string>
                    <string>2832</string>
                    <string>2833</string>
                    <string>2834</string>
                    <string>2835</string>
                    <string>2836</string>
                    <string>2837</string>
                    <string>2838</string>
                    <string>2839</string>
                    <string>2840</string>
                    <string>2841</string>
                    <string>2842</string>
                    <string>2843</string>
                    <string>2844</string>
                    <string>2845</string>
                    <string>2846</string>
                    <string>2847</string>
                    <string>2848</string>
                    <string>2849</string>
                    <string>2850</string>
                    <string>2851</string>
                    <string>2852</string>
                    <string>2853</string>
                    <string>2854</string>
                    <string>2855</string>
                </array>
            </dict>
            <dict>
                <key>id</key>
                <string>3008</string>
                <key>sprites</key>
                <array>
                    <string>3009</string>
                </array>
            </dict>
            <dict>
                <key>id</key>
                <string>3160</string>
                <key>sprites</key>
                <array>
                    <string>3161</string>
                    <string>3162</string>
                    <string>3163</string>
                    <string>3164</string>
                    <string>3165</string>
                    <string>3166</string>
                    <string>3167</string>
                    <string>3168</string>
                </array>
            </dict>
            <dict>
                <key>id</key>
                <string>3181</string>
                <key>sprites</key>
                <array>
                    <string>3182</string>
                </array>
            </dict>
            <dict>
                <key>id</key>
                <string>3206</string>
                <key>sprites</key>
                <array>
                    <string>3207</string>
                </array>
            </dict>
            <dict>
                <key>id</key>
                <string>3266</string>
                <key>sprites</key>
                <array>
                    <string>3267</string>
                </array>
            </dict>
            <dict>
                <key>id</key>
                <string>3352</string>
                <key>sprites</key>
                <array>
                    <string>3353</string>
                </array>
            </dict>
            <dict>
                <key>id</key>
                <string>3420</string>
                <key>sprites</key>
                <array>
                    <string>3421</string>
                </array>
            </dict>
            <dict>
                <key>id</key>
                <string>3424</string>
                <key>sprites</key>
                <array>
                    <string>3425</string>
                </array>
            </dict>
            <dict>
                <key>id</key>
                <string>3535</string>
                <key>sprites</key>
                <array>
                    <string>3536</string>
                </array>
            </dict>
            <dict>
                <key>id</key>
                <string>3541</string>
                <key>sprites</key>
                <array>
                    <string>3542</string>
                </array>
            </dict>
            <dict>
                <key>id</key>
                <string>3549</string>
                <key>sprites</key>
                <array>
                    <string>3550</string>
                </array>
            </dict>
            <dict>
                <key>id</key>
                <string>3636</string>
                <key>sprites</key>
                <array>
                    <string>3637</string>
                </array>
            </dict>
            <dict>
                <key>id</key>
                <string>3692</string>
                <key>sprites</key>
                <array>
                    <string>3693</string>
                    <string>3694</string>
                    <string>3695</string>
                    <string>3696</string>
                    <string>3697</string>
                    <string>3698</string>
                    <string>3699</string>
                    <string>3700</string>
                </array>
            </dict>
            <dict>
                <key>id</key>
                <string>3755</string>
                <key>sprites</key>
                <array>
                    <string>3756</string>
                </array>
            </dict>
            <dict>
                <key>id</key>
                <string>3766</string>
                <key>sprites</key>
                <array>
                    <string>3767</string>
                </array>
            </dict>
            <dict>
                <key>id</key>
                <string>3798</string>
                <key>sprites</key>
                <array>
                    <string>3799</string>
                    <string>3800</string>
                    <string>3801</string>
                    <string>3802</string>
                    <string>3803</string>
                    <string>3804</string>
                    <string>3805</string>
                    <string>3806</string>
                    <string>3807</string>
                    <string>3808</string>
                    <string>3809</string>
                    <string>3810</string>
                    <string>3811</string>
                    <string>3812</string>
                </array>
            </dict>
            <dict>
                <key>id</key>
                <string>3831</string>
                <key>sprites</key>
                <array>
                    <string>3832</string>
                </array>
            </dict>
            <dict>
                <key>id</key>
                <string>3860</string>
                <key>sprites</key>
                <array>
                    <string>3861</string>
                </array>
            </dict>
            <dict>
                <key>id</key>
                <string>3871</string>
                <key>sprites</key>
                <array>
                    <string>3872</string>
                </array>
            </dict>
            <dict>
                <key>id</key>
                <string>3883</string>
                <key>sprites</key>
                <array>
                    <string>3884</string>
                </array>
            </dict>
            <dict>
                <key>id</key>
                <string>3895</string>
                <key>sprites</key>
                <array>
                    <string>3896</string>
                </array>
            </dict>
            <dict>
                <key>id</key>
                <string>3908</string>
                <key>sprites</key>
                <array>
                    <string>3909</string>
                </array>
            </dict>
            <dict>
                <key>id</key>
                <string>3931</string>
                <key>sprites</key>
                <array>
                    <string>3932</string>
                </array>
            </dict>
            <dict>
                <key>id</key>
                <string>3954</string>
                <key>sprites</key>
                <array>
                    <string>3955</string>
                    <string>3956</string>
                </array>
            </dict>
            <dict>
                <key>id</key>
                <string>3967</string>
                <key>sprites</key>
                <array>
                    <string>3968</string>
                </array>
            </dict>
            <dict>
                <key>id</key>
                <string>3978</string>
                <key>sprites</key>
                <array>
                    <string>3979</string>
                </array>
            </dict>
            <dict>
                <key>id</key>
                <string>4139</string>
                <key>sprites</key>
                <array>
                    <string>4140</string>
                </array>
            </dict>
            <dict>
                <key>id</key>
                <string>4154</string>
                <key>sprites</key>
                <array>
                    <string>4155</string>
                </array>
            </dict>
            <dict>
                <key>id</key>
                <string>4166</string>
                <key>sprites</key>
                <array>
                    <string>4167</string>
                </array>
            </dict>
            <dict>
                <key>id</key>
                <string>4204</string>
                <key>sprites</key>
                <array>
                    <string>4205</string>
                </array>
            </dict>
            <dict>
                <key>id</key>
                <string>4394</string>
                <key>sprites</key>
                <array>
                    <string>4395</string>
                    <string>4396</string>
                    <string>4397</string>
                    <string>4398</string>
                </array>
            </dict>
            <dict>
                <key>id</key>
                <string>4409</string>
                <key>sprites</key>
                <array>
                    <string>4410</string>
                </array>
            </dict>
            <dict>
                <key>id</key>
                <string>4439</string>
                <key>sprites</key>
                <array>
                    <string>4440</string>
                </array>
            </dict>
            <dict>
                <key>id</key>
                <string>4466</string>
                <key>sprites</key>
                <array>
                    <string>4467</string>
                </array>
            </dict>
            <dict>
                <key>id</key>
                <string>4861</string>
                <key>sprites</key>
                <array>
                    <string>4862</string>
                </array>
            </dict>
        </array>
    </dict>
</plist>
